andor2.c
andor2.pyx
setup.py
andor.egg-info/PKG-INFO
andor.egg-info/SOURCES.txt
andor.egg-info/dependency_links.txt
andor.egg-info/top_level.txt