Metadata-Version: 1.1
Name: andor
Version: 1.11
Summary: Object-oriented interface for Andor EMCCD cameras
Home-page: UNKNOWN
Author: Guillaume Lepert
Author-email: guillaume.lepert07@imperial.ac.uk
License: UNKNOWN
Platform: linux
Classifier: Development Status :: 5 - Production/Stable
Classifier: Environment :: Console
Classifier: Intended Audience :: Science/Research
Classifier: License :: OSI Approved :: MIT License
Classifier: Natural Language :: English
Classifier: Operating System :: POSIX :: Linux
Classifier: Programming Language :: C
Classifier: Programming Language :: Cython
Classifier: Programming Language :: Python :: 2.7
Classifier: Topic :: Home Automation
Classifier: Topic :: Scientific/Engineering
Requires: numpy
Requires: cython
Requires: h5py
